autotrain_vision/__init__.py
autotrain_vision/auto_train.py
autotrain_vision/available_cam.py
autotrain_vision/new_data.py
autotrain_vision/roboflow_bb.py
autotrain_vision/utils_aug.py
autotrain_vision-0.0.3.dist-info/METADATA
autotrain_vision-0.0.3.dist-info/WHEEL
autotrain_vision-0.0.3.dist-info/top_level.txt
autotrain_vision-0.0.3.dist-info/RECORD
