Metadata-Version: 2.1
Name: autotrain_vision
Version: 0.0.3
Summary: Automate the manual labelling and training for supervised models, YOLOv8
Author-email: Jiya <jiyanagpal816@gmail.com>
Classifier: Programming Language :: Python :: 3
Classifier: License :: OSI Approved :: GNU General Public License v3 (GPLv3)
Classifier: Operating System :: OS Independent
Requires-Python: >=3.8
Requires-Dist: albumentations ==1.4.7
Requires-Dist: imgaug ==0.4.0
Requires-Dist: numpy ==1.24.4
Requires-Dist: ultralytics ==8.2.20
Requires-Dist: opencv-python ==4.10.0.84
Requires-Dist: Pillow
Requires-Dist: PyYAML ==6.0.2
Requires-Dist: split-folders
Requires-Dist: torch
Requires-Dist: transformers ==4.46.3
